pygifconvt_WangMooNo/MooNo_converter.py
pygifconvt_WangMooNo/__init__.py
pygifconvt_Wang_Moo_No-1.0.1.dist-info/LICENSE
pygifconvt_Wang_Moo_No-1.0.1.dist-info/METADATA
pygifconvt_Wang_Moo_No-1.0.1.dist-info/WHEEL
pygifconvt_Wang_Moo_No-1.0.1.dist-info/top_level.txt
pygifconvt_Wang_Moo_No-1.0.1.dist-info/RECORD
